MANIFEST.in
README.rst
setup.py
pycodeanalyzer/__init__.py
pycodeanalyzer/__main__.py
pycodeanalyzer/injection.py
pycodeanalyzer.egg-info/PKG-INFO
pycodeanalyzer.egg-info/SOURCES.txt
pycodeanalyzer.egg-info/dependency_links.txt
pycodeanalyzer.egg-info/entry_points.txt
pycodeanalyzer.egg-info/requires.txt
pycodeanalyzer.egg-info/top_level.txt
pycodeanalyzer/core/__init__.py
pycodeanalyzer/core/abstraction/__init__.py
pycodeanalyzer/core/abstraction/objects.py
pycodeanalyzer/core/analyzer/__init__.py
pycodeanalyzer/core/analyzer/dependancy.py
pycodeanalyzer/core/analyzer/identification.py
pycodeanalyzer/core/analyzer/search.py
pycodeanalyzer/core/configuration/__init__.py
pycodeanalyzer/core/configuration/configuration.py
pycodeanalyzer/core/console/__init__.py
pycodeanalyzer/core/console/console.py
pycodeanalyzer/core/diagrams/__init__.py
pycodeanalyzer/core/diagrams/iclassdiagrambuild.py
pycodeanalyzer/core/diagrams/mermaid.py
pycodeanalyzer/core/diagrams/plantuml.py
pycodeanalyzer/core/encoding/__init__.py
pycodeanalyzer/core/encoding/encodings.py
pycodeanalyzer/core/engine/__init__.py
pycodeanalyzer/core/engine/engine.py
pycodeanalyzer/core/filetree/__init__.py
pycodeanalyzer/core/filetree/filefetcher.py
pycodeanalyzer/core/json/__init__.py
pycodeanalyzer/core/json/pickler.py
pycodeanalyzer/core/languages/__init__.py
pycodeanalyzer/core/languages/analyzer.py
pycodeanalyzer/core/languages/extensions.py
pycodeanalyzer/core/languages/filedispatcher.py
pycodeanalyzer/core/languages/analyzers/__init__.py
pycodeanalyzer/core/languages/analyzers/cppanalyzer.py
pycodeanalyzer/core/languages/analyzers/javaanalyzer.py
pycodeanalyzer/core/languages/analyzers/kotlinanalyzer.py
pycodeanalyzer/core/languages/analyzers/pythonanalyzer.py
pycodeanalyzer/core/logging/__init__.py
pycodeanalyzer/core/logging/loggerfactory.py
pycodeanalyzer/core/utils/__init__.py
pycodeanalyzer/core/utils/containers.py
pycodeanalyzer/core/utils/math.py
pycodeanalyzer/ui/__init__.py
pycodeanalyzer/ui/app.py
pycodeanalyzer/ui/engineinterface.py
pycodeanalyzer/ui/socketlistener.py
pycodeanalyzer/ui/web/static/css/default.css
pycodeanalyzer/ui/web/static/css/libs/highlight.11.5.0.default.min.css
