Metadata-Version: 2.1
Name: pycodeanalyzer
Version: 0.0.6
Summary: Code analyzer to get information to help developers to understand how projects works.
Home-page: https://github.com/miong/pycodeanalyzer
Author: Giovanni Mion
Author-email: mion.ggb@gmail.com
License: MIT
Platform: UNKNOWN
Classifier: Development Status :: 2 - Pre-Alpha
Classifier: License :: OSI Approved :: MIT License
Classifier: Programming Language :: Python :: 3
Classifier: Programming Language :: Python :: 3.7
Provides-Extra: dev
